acs_crawler/__init__.py
acs_crawler/config.py
acs_crawler/crawler_service.py
acs_crawler/api/__init__.py
acs_crawler/api/main.py
acs_crawler/api/static/functional_words.json
acs_crawler/api/static/css/dashboard.css
acs_crawler/api/static/js/api.js
acs_crawler/api/static/js/charts.js
acs_crawler/api/static/js/dashboard.js
acs_crawler/api/static/js/papers-charts.js
acs_crawler/api/static/js/papers-filter.js
acs_crawler/api/static/js/ui.js
acs_crawler/api/templates/base.html
acs_crawler/api/templates/index.html
acs_crawler/api/templates/index_old.html
acs_crawler/api/templates/jobs.html
acs_crawler/api/templates/paper_detail.html
acs_crawler/api/templates/papers.html
acs_crawler/api/templates/papers_old.html
acs_crawler/data/acs_journals.json
acs_crawler/models/__init__.py
acs_crawler/models/paper.py
acs_crawler/scrapers/__init__.py
acs_crawler/scrapers/paper_scraper.py
acs_crawler/scrapers/selenium_scraper.py
acs_crawler/storage/__init__.py
acs_crawler/storage/sqlite_storage.py
acs_crawler/utils/__init__.py
acs_crawler/utils/search_builder.py
acs_crawler-0.1.3.dist-info/LICENSE
acs_crawler-0.1.3.dist-info/METADATA
acs_crawler-0.1.3.dist-info/WHEEL
acs_crawler-0.1.3.dist-info/top_level.txt
acs_crawler-0.1.3.dist-info/RECORD
