Metadata-Version: 2.1
Name: acs-crawler
Version: 0.1.3
Summary: A professional crawler for American Chemical Society papers with modern web dashboard
Author-email: Xufan Gao <gxf1212@zju.edu.cn>
License: MIT
Project-URL: Homepage, https://github.com/gxf1212/ACS_crawler
Project-URL: Documentation, https://acs-crawler.readthedocs.io/
Project-URL: Repository, https://github.com/gxf1212/ACS_crawler
Project-URL: Issues, https://github.com/gxf1212/ACS_crawler/issues
Project-URL: Changelog, https://github.com/gxf1212/ACS_crawler/blob/main/CHANGELOG.md
Project-URL: PyPI, https://pypi.org/project/acs_crawler/
Keywords: acs,crawler,web-scraping,research,chemistry,papers,scientific-research
Classifier: Development Status :: 3 - Alpha
Classifier: Intended Audience :: Science/Research
Classifier: Intended Audience :: Developers
Classifier: Topic :: Scientific/Engineering :: Chemistry
Classifier: Topic :: Scientific/Engineering :: Information Analysis
Classifier: License :: OSI Approved :: MIT License
Classifier: Programming Language :: Python :: 3
Classifier: Programming Language :: Python :: 3.9
Classifier: Programming Language :: Python :: 3.10
Classifier: Programming Language :: Python :: 3.11
Classifier: Operating System :: OS Independent
Classifier: Framework :: FastAPI
Requires-Python: >=3.9
License-File: LICENSE
Requires-Dist: requests >=2.31.0
Requires-Dist: beautifulsoup4 >=4.12.0
Requires-Dist: lxml >=5.1.0
Requires-Dist: fastapi >=0.109.0
Requires-Dist: uvicorn[standard] >=0.27.0
Requires-Dist: jinja2 >=3.1.3
Requires-Dist: pydantic >=2.6.0
Requires-Dist: python-multipart >=0.0.9
Requires-Dist: httpx >=0.26.0
Requires-Dist: selenium >=4.15.0
Requires-Dist: webdriver-manager >=4.0.1
Requires-Dist: openpyxl >=3.1.0
Requires-Dist: python-dotenv >=1.0.0
Provides-Extra: dev
Requires-Dist: pytest >=8.0.0 ; extra == 'dev'
Requires-Dist: pytest-cov >=4.1.0 ; extra == 'dev'
Requires-Dist: pytest-asyncio >=0.23.0 ; extra == 'dev'
Requires-Dist: black >=24.1.0 ; extra == 'dev'
Requires-Dist: mypy >=1.8.0 ; extra == 'dev'
Requires-Dist: types-requests >=2.31.0 ; extra == 'dev'
Requires-Dist: types-beautifulsoup4 >=4.12.0 ; extra == 'dev'
